<?xml version="1.0" encoding="utf-8"?>
<!DOCTYPE hibernate-mapping PUBLIC "-//Hibernate/Hibernate Mapping DTD 3.0//EN"
"http://hibernate.sourceforge.net/hibernate-mapping-3.0.dtd">
<!-- 
    Mapping file autogenerated by MyEclipse Persistence Tools
-->
<hibernate-mapping>
    <class name="com.youdanle.entity.Car" table="CAR" schema="SXND">
        <id name="cid" type="java.lang.Integer">
            <column name="CID" precision="8" scale="0" />
            <generator class="sequence">
            	<param name="sequence">user_seq</param>
            </generator>
        </id>
        <many-to-one name="cartype" class="com.youdanle.entity.Cartype" fetch="select">
            <column name="CTYPE" precision="8" scale="0" />
        </many-to-one>
        <property name="cname" type="java.lang.String">
            <column name="CNAME" length="20" />
        </property>
        <property name="loginname" type="java.lang.String">
            <column name="LOGINNAME" length="24" />
        </property>
        <property name="loginpass" type="java.lang.String">
            <column name="LOGINPASS" length="32" />
        </property>
        <property name="type" type="java.lang.String">
            <column name="TYPE" length="4" />
        </property>
        <property name="phone" type="java.lang.String">
            <column name="PHONE" length="22" />
        </property>
        <property name="cnumber" type="java.lang.String">
            <column name="CNUMBER" length="20" />
        </property>
        <property name="caddr" type="java.lang.String">
            <column name="CADDR" length="400" />
        </property>
        <property name="cload" type="java.lang.Double">
            <column name="CLOAD" precision="8" />
        </property>
        <property name="cstatus" type="java.lang.String">
            <column name="CSTATUS" length="4" />
        </property>
        <property name="cvip" type="java.lang.String">
            <column name="CVIP" length="40" />
        </property>
        <property name="images" type="java.lang.String">
            <column name="IMAGES" length="1000" />
        </property>
        <property name="csize" type="java.lang.Double">
            <column name="CSIZE" precision="8" />
        </property>
        <property name="collect" type="java.lang.String">
            <column name="COLLECT" length="1000" />
        </property>
        <set name="forums" inverse="true">
            <key>
                <column name="CID" precision="8" scale="0" />
            </key>
            <one-to-many class="com.youdanle.entity.Forum" />
        </set>
        <set name="replies" inverse="true">
            <key>
                <column name="CID" precision="8" scale="0" />
            </key>
            <one-to-many class="com.youdanle.entity.Reply" />
        </set>
        <set name="getorders" inverse="true">
            <key>
                <column name="CID" precision="8" scale="0" />
            </key>
            <one-to-many class="com.youdanle.entity.Getorder" />
        </set>
    </class>
</hibernate-mapping>
